layermake/__init__.py
layermake/binary.py
layermake/bundler.py
layermake/cli.py
layermake/cmd.py
layermake/logger.py
layermake/node.py
layermake/publisher.py
layermake/python.py
layermake-0.0.9.dist-info/LICENSE.md
layermake-0.0.9.dist-info/METADATA
layermake-0.0.9.dist-info/WHEEL
layermake-0.0.9.dist-info/entry_points.txt
layermake-0.0.9.dist-info/top_level.txt
layermake-0.0.9.dist-info/RECORD
