Metadata-Version: 2.1
Name: layermake
Version: 0.0.9
Summary: CLI toolkit for bundling AWS Lambda layers
Home-page: https://github.com/ericmaustin/layermake
Author: Eric Austin
Author-email: eric.m.austin@gmail.com
License: MIT
Requires-Python: >=3.8
License-File: LICENSE.md
Requires-Dist: Click
Requires-Dist: boto3
Requires-Dist: rich
